{
  "INVENTORY" : {
    "skinTabActiveBgColor" : "#4ABDFF",
    "lastModificationDate" : "newDate",
    "code" : "INVENTORY",
    "skinTabTextColor" : "",
    "createdByUser" : {
      "getter" : "getByUsername",
      "innerClass" : "User",
      "params" : [ {
        "getter" : "valueOf",
        "innerClass" : "String",
        "params" : "root"
      }, {
        "getter" : "getByHierarchyCode",
        "innerClass" : "Group",
        "params" : ">root"
      } ]
    },
    "skinTabBgColor" : "#000000",
    "name" : "Inventory",
    "icon" : "tab-icon-tenant-retail",
    "displayOrder" : 3,
    "skinTabActiveTextColor" : "#000000",
    "creationDate" : "newDate",
    "group" : {
      "getter" : "getByHierarchyCode",
      "innerClass" : "Group",
      "params" : "${tenant.hierarchyCode}"
    }
  }
}