{
  "CountedTo" : {
    "autoComplete" : false,
    "reportDefinition" : {
      "getter" : "getByCodeAndHierarchyCode",
      "innerClass" : "ReportDefinition",
      "params" : [ {
        "getter" : "valueOf",
        "innerClass" : "String",
        "params" : "REALTIMEDISCREPANCY"
      }, {
        "getter" : "valueOf",
        "innerClass" : "String",
        "params" : "${tenant.hierarchyCode}"
      } ]
    },
    "propertyName" : "Retail_SOHQTY",
    "editable" : true,
    "displayOrder" : 14,
    "label" : "CountedTo",
    "thingType" : {
      "getter" : "getByCodeAndGroup",
      "innerClass" : "ThingType",
      "params" : [ {
        "getter" : "valueOf",
        "innerClass" : "String",
        "params" : "SOH"
      }, {
        "getter" : "getByHierarchyCode",
        "innerClass" : "Group",
        "params" : "${tenant.hierarchyCode}"
      } ]
    },
    "thingTypeField" : {
      "getter" : "getByNameAndThingType",
      "innerClass" : "ThingTypeField",
      "params" : [ {
        "getter" : "valueOf",
        "innerClass" : "String",
        "params" : "Retail_SOHQTY"
      }, {
        "getter" : "getByCodeAndGroup",
        "innerClass" : "ThingType",
        "params" : [ {
          "getter" : "valueOf",
          "innerClass" : "String",
          "params" : "SOH"
        }, {
          "getter" : "getByHierarchyCode",
          "innerClass" : "Group",
          "params" : "${tenant.hierarchyCode}"
        } ]
      } ]
    },
    "fieldType" : 4,
    "value" : "",
    "operator" : "<="
  },
  "RemainingFrom" : {
    "autoComplete" : false,
    "reportDefinition" : {
      "getter" : "getByCodeAndHierarchyCode",
      "innerClass" : "ReportDefinition",
      "params" : [ {
        "getter" : "valueOf",
        "innerClass" : "String",
        "params" : "REALTIMEDISCREPANCY"
      }, {
        "getter" : "valueOf",
        "innerClass" : "String",
        "params" : "${tenant.hierarchyCode}"
      } ]
    },
    "propertyName" : "Retail_SOHQTY",
    "editable" : true,
    "displayOrder" : 11,
    "label" : "RemainingFrom",
    "thingType" : {
      "getter" : "getByCodeAndGroup",
      "innerClass" : "ThingType",
      "params" : [ {
        "getter" : "valueOf",
        "innerClass" : "String",
        "params" : "SOH"
      }, {
        "getter" : "getByHierarchyCode",
        "innerClass" : "Group",
        "params" : "${tenant.hierarchyCode}"
      } ]
    },
    "thingTypeField" : {
      "getter" : "getByNameAndThingType",
      "innerClass" : "ThingTypeField",
      "params" : [ {
        "getter" : "valueOf",
        "innerClass" : "String",
        "params" : "Retail_SOHQTY"
      }, {
        "getter" : "getByCodeAndGroup",
        "innerClass" : "ThingType",
        "params" : [ {
          "getter" : "valueOf",
          "innerClass" : "String",
          "params" : "SOH"
        }, {
          "getter" : "getByHierarchyCode",
          "innerClass" : "Group",
          "params" : "${tenant.hierarchyCode}"
        } ]
      } ]
    },
    "fieldType" : 4,
    "value" : "",
    "operator" : ">="
  },
  "SortBy" : {
    "autoComplete" : false,
    "reportDefinition" : {
      "getter" : "getByCodeAndHierarchyCode",
      "innerClass" : "ReportDefinition",
      "params" : [ {
        "getter" : "valueOf",
        "innerClass" : "String",
        "params" : "REALTIMEDISCREPANCY"
      }, {
        "getter" : "valueOf",
        "innerClass" : "String",
        "params" : "${tenant.hierarchyCode}"
      } ]
    },
    "propertyName" : "name",
    "editable" : false,
    "displayOrder" : 15,
    "label" : "SortBy",
    "thingType" : {
      "getter" : "getByCodeAndGroup",
      "innerClass" : "ThingType",
      "params" : [ {
        "getter" : "valueOf",
        "innerClass" : "String",
        "params" : "DD_SORTBY"
      }, {
        "getter" : "getByHierarchyCode",
        "innerClass" : "Group",
        "params" : "${tenant.hierarchyCode}"
      } ]
    },
    "thingTypeField" : null,
    "fieldType" : 1,
    "value" : "Remaining",
    "operator" : "="
  },
  "RTI Code" : {
    "autoComplete" : false,
    "reportDefinition" : {
      "getter" : "getByCodeAndHierarchyCode",
      "innerClass" : "ReportDefinition",
      "params" : [ {
        "getter" : "valueOf",
        "innerClass" : "String",
        "params" : "REALTIMEDISCREPANCY"
      }, {
        "getter" : "valueOf",
        "innerClass" : "String",
        "params" : "${tenant.hierarchyCode}"
      } ]
    },
    "propertyName" : "Retail_Product_SKU",
    "editable" : true,
    "displayOrder" : 6,
    "label" : "RTI Code",
    "thingType" : {
      "getter" : "getByCodeAndGroup",
      "innerClass" : "ThingType",
      "params" : [ {
        "getter" : "valueOf",
        "innerClass" : "String",
        "params" : "SOH"
      }, {
        "getter" : "getByHierarchyCode",
        "innerClass" : "Group",
        "params" : "${tenant.hierarchyCode}"
      } ]
    },
    "thingTypeField" : {
      "getter" : "getByNameAndThingType",
      "innerClass" : "ThingTypeField",
      "params" : [ {
        "getter" : "valueOf",
        "innerClass" : "String",
        "params" : "Retail_Product_SKU"
      }, {
        "getter" : "getByCodeAndGroup",
        "innerClass" : "ThingType",
        "params" : [ {
          "getter" : "valueOf",
          "innerClass" : "String",
          "params" : "SOH"
        }, {
          "getter" : "getByHierarchyCode",
          "innerClass" : "Group",
          "params" : "${tenant.hierarchyCode}"
        } ]
      } ]
    },
    "fieldType" : 1,
    "value" : "",
    "operator" : "="
  },
  "SortOrder" : {
    "autoComplete" : false,
    "reportDefinition" : {
      "getter" : "getByCodeAndHierarchyCode",
      "innerClass" : "ReportDefinition",
      "params" : [ {
        "getter" : "valueOf",
        "innerClass" : "String",
        "params" : "REALTIMEDISCREPANCY"
      }, {
        "getter" : "valueOf",
        "innerClass" : "String",
        "params" : "${tenant.hierarchyCode}"
      } ]
    },
    "propertyName" : "name",
    "editable" : false,
    "displayOrder" : 16,
    "label" : "SortOrder",
    "thingType" : {
      "getter" : "getByCodeAndGroup",
      "innerClass" : "ThingType",
      "params" : [ {
        "getter" : "valueOf",
        "innerClass" : "String",
        "params" : "DD_SORTORDER"
      }, {
        "getter" : "getByHierarchyCode",
        "innerClass" : "Group",
        "params" : "${tenant.hierarchyCode}"
      } ]
    },
    "thingTypeField" : null,
    "fieldType" : 1,
    "value" : "Ascending",
    "operator" : "="
  },
  "ExpectedTo" : {
    "autoComplete" : false,
    "reportDefinition" : {
      "getter" : "getByCodeAndHierarchyCode",
      "innerClass" : "ReportDefinition",
      "params" : [ {
        "getter" : "valueOf",
        "innerClass" : "String",
        "params" : "REALTIMEDISCREPANCY"
      }, {
        "getter" : "valueOf",
        "innerClass" : "String",
        "params" : "${tenant.hierarchyCode}"
      } ]
    },
    "propertyName" : "Retail_SOHQTY",
    "editable" : true,
    "displayOrder" : 10,
    "label" : "ExpectedTo",
    "thingType" : {
      "getter" : "getByCodeAndGroup",
      "innerClass" : "ThingType",
      "params" : [ {
        "getter" : "valueOf",
        "innerClass" : "String",
        "params" : "SOH"
      }, {
        "getter" : "getByHierarchyCode",
        "innerClass" : "Group",
        "params" : "${tenant.hierarchyCode}"
      } ]
    },
    "thingTypeField" : {
      "getter" : "getByNameAndThingType",
      "innerClass" : "ThingTypeField",
      "params" : [ {
        "getter" : "valueOf",
        "innerClass" : "String",
        "params" : "Retail_SOHQTY"
      }, {
        "getter" : "getByCodeAndGroup",
        "innerClass" : "ThingType",
        "params" : [ {
          "getter" : "valueOf",
          "innerClass" : "String",
          "params" : "SOH"
        }, {
          "getter" : "getByHierarchyCode",
          "innerClass" : "Group",
          "params" : "${tenant.hierarchyCode}"
        } ]
      } ]
    },
    "fieldType" : 4,
    "value" : "",
    "operator" : "<="
  },
  "Thing Owner Group" : {
    "autoComplete" : false,
    "reportDefinition" : {
      "getter" : "getByCodeAndHierarchyCode",
      "innerClass" : "ReportDefinition",
      "params" : [ {
        "getter" : "valueOf",
        "innerClass" : "String",
        "params" : "REALTIMEDISCREPANCY"
      }, {
        "getter" : "valueOf",
        "innerClass" : "String",
        "params" : "${tenant.hierarchyCode}"
      } ]
    },
    "propertyName" : "visibility.thingOwnerGroup",
    "editable" : false,
    "displayOrder" : 3,
    "label" : "Thing Owner Group",
    "thingType" : null,
    "thingTypeField" : null,
    "fieldType" : 0,
    "value" : "false",
    "operator" : "="
  },
  "Date" : {
    "autoComplete" : false,
    "reportDefinition" : {
      "getter" : "getByCodeAndHierarchyCode",
      "innerClass" : "ReportDefinition",
      "params" : [ {
        "getter" : "valueOf",
        "innerClass" : "String",
        "params" : "REALTIMEDISCREPANCY"
      }, {
        "getter" : "valueOf",
        "innerClass" : "String",
        "params" : "${tenant.hierarchyCode}"
      } ]
    },
    "propertyName" : "relativeDate",
    "editable" : false,
    "displayOrder" : 1,
    "label" : "Date",
    "thingType" : null,
    "thingTypeField" : null,
    "fieldType" : 0,
    "value" : "NOW",
    "operator" : ""
  },
  "CountedFrom" : {
    "autoComplete" : false,
    "reportDefinition" : {
      "getter" : "getByCodeAndHierarchyCode",
      "innerClass" : "ReportDefinition",
      "params" : [ {
        "getter" : "valueOf",
        "innerClass" : "String",
        "params" : "REALTIMEDISCREPANCY"
      }, {
        "getter" : "valueOf",
        "innerClass" : "String",
        "params" : "${tenant.hierarchyCode}"
      } ]
    },
    "propertyName" : "Retail_SOHQTY",
    "editable" : true,
    "displayOrder" : 13,
    "label" : "CountedFrom",
    "thingType" : {
      "getter" : "getByCodeAndGroup",
      "innerClass" : "ThingType",
      "params" : [ {
        "getter" : "valueOf",
        "innerClass" : "String",
        "params" : "SOH"
      }, {
        "getter" : "getByHierarchyCode",
        "innerClass" : "Group",
        "params" : "${tenant.hierarchyCode}"
      } ]
    },
    "thingTypeField" : {
      "getter" : "getByNameAndThingType",
      "innerClass" : "ThingTypeField",
      "params" : [ {
        "getter" : "valueOf",
        "innerClass" : "String",
        "params" : "Retail_SOHQTY"
      }, {
        "getter" : "getByCodeAndGroup",
        "innerClass" : "ThingType",
        "params" : [ {
          "getter" : "valueOf",
          "innerClass" : "String",
          "params" : "SOH"
        }, {
          "getter" : "getByHierarchyCode",
          "innerClass" : "Group",
          "params" : "${tenant.hierarchyCode}"
        } ]
      } ]
    },
    "fieldType" : 4,
    "value" : "",
    "operator" : ">="
  },
  "Thing Type" : {
    "autoComplete" : false,
    "reportDefinition" : {
      "getter" : "getByCodeAndHierarchyCode",
      "innerClass" : "ReportDefinition",
      "params" : [ {
        "getter" : "valueOf",
        "innerClass" : "String",
        "params" : "REALTIMEDISCREPANCY"
      }, {
        "getter" : "valueOf",
        "innerClass" : "String",
        "params" : "${tenant.hierarchyCode}"
      } ]
    },
    "propertyName" : "thingType.id",
    "editable" : false,
    "displayOrder" : 2,
    "label" : "Thing Type",
    "thingType" : null,
    "thingTypeField" : null,
    "fieldType" : 0,
    "value" : {
      "innerMethod" : "getThingTypeId",
      "params" : [ {
        "getter" : "valueOf",
        "innerClass" : "String",
        "params" : "ITEM"
      }, {
        "getter" : "valueOf",
        "innerClass" : "String",
        "params" : "${tenant.hierarchyCode}"
      } ]
    },
    "operator" : "="
  },
  "Thing Facility Map" : {
    "autoComplete" : false,
    "reportDefinition" : {
      "getter" : "getByCodeAndHierarchyCode",
      "innerClass" : "ReportDefinition",
      "params" : [ {
        "getter" : "valueOf",
        "innerClass" : "String",
        "params" : "REALTIMEDISCREPANCY"
      }, {
        "getter" : "valueOf",
        "innerClass" : "String",
        "params" : "${tenant.hierarchyCode}"
      } ]
    },
    "propertyName" : "visibility.facilityMap",
    "editable" : false,
    "displayOrder" : 4,
    "label" : "Thing Facility Map",
    "thingType" : null,
    "thingTypeField" : null,
    "fieldType" : 0,
    "value" : "true",
    "operator" : "="
  },
  "ExpectedFrom" : {
    "autoComplete" : false,
    "reportDefinition" : {
      "getter" : "getByCodeAndHierarchyCode",
      "innerClass" : "ReportDefinition",
      "params" : [ {
        "getter" : "valueOf",
        "innerClass" : "String",
        "params" : "REALTIMEDISCREPANCY"
      }, {
        "getter" : "valueOf",
        "innerClass" : "String",
        "params" : "${tenant.hierarchyCode}"
      } ]
    },
    "propertyName" : "Retail_SOHQTY",
    "editable" : true,
    "displayOrder" : 9,
    "label" : "ExpectedFrom",
    "thingType" : {
      "getter" : "getByCodeAndGroup",
      "innerClass" : "ThingType",
      "params" : [ {
        "getter" : "valueOf",
        "innerClass" : "String",
        "params" : "SOH"
      }, {
        "getter" : "getByHierarchyCode",
        "innerClass" : "Group",
        "params" : "${tenant.hierarchyCode}"
      } ]
    },
    "thingTypeField" : {
      "getter" : "getByNameAndThingType",
      "innerClass" : "ThingTypeField",
      "params" : [ {
        "getter" : "valueOf",
        "innerClass" : "String",
        "params" : "Retail_SOHQTY"
      }, {
        "getter" : "getByCodeAndGroup",
        "innerClass" : "ThingType",
        "params" : [ {
          "getter" : "valueOf",
          "innerClass" : "String",
          "params" : "SOH"
        }, {
          "getter" : "getByHierarchyCode",
          "innerClass" : "Group",
          "params" : "${tenant.hierarchyCode}"
        } ]
      } ]
    },
    "fieldType" : 4,
    "value" : "",
    "operator" : ">="
  },
  "Facility" : {
    "autoComplete" : false,
    "reportDefinition" : {
      "getter" : "getByCodeAndHierarchyCode",
      "innerClass" : "ReportDefinition",
      "params" : [ {
        "getter" : "valueOf",
        "innerClass" : "String",
        "params" : "REALTIMEDISCREPANCY"
      }, {
        "getter" : "valueOf",
        "innerClass" : "String",
        "params" : "${tenant.hierarchyCode}"
      } ]
    },
    "propertyName" : "zoneLocalMap.id",
    "editable" : true,
    "displayOrder" : 8,
    "label" : "Facility",
    "thingType" : {
      "getter" : "getByCodeAndGroup",
      "innerClass" : "ThingType",
      "params" : [ {
        "getter" : "valueOf",
        "innerClass" : "String",
        "params" : "ITEM"
      }, {
        "getter" : "getByHierarchyCode",
        "innerClass" : "Group",
        "params" : "${tenant.hierarchyCode}"
      } ]
    },
    "thingTypeField" : {
      "getter" : "getByNameAndThingType",
      "innerClass" : "ThingTypeField",
      "params" : [ {
        "getter" : "valueOf",
        "innerClass" : "String",
        "params" : "zone"
      }, {
        "getter" : "getByCodeAndGroup",
        "innerClass" : "ThingType",
        "params" : [ {
          "getter" : "valueOf",
          "innerClass" : "String",
          "params" : "ITEM"
        }, {
          "getter" : "getByHierarchyCode",
          "innerClass" : "Group",
          "params" : "${tenant.hierarchyCode}"
        } ]
      } ]
    },
    "fieldType" : 1,
    "value" : null,
    "operator" : "="
  },
  "RTI Type" : {
    "autoComplete" : false,
    "reportDefinition" : {
      "getter" : "getByCodeAndHierarchyCode",
      "innerClass" : "ReportDefinition",
      "params" : [ {
        "getter" : "valueOf",
        "innerClass" : "String",
        "params" : "REALTIMEDISCREPANCY"
      }, {
        "getter" : "valueOf",
        "innerClass" : "String",
        "params" : "${tenant.hierarchyCode}"
      } ]
    },
    "propertyName" : "Retail_Product_Level1Name",
    "editable" : true,
    "displayOrder" : 5,
    "label" : "RTI Type",
    "thingType" : {
      "getter" : "getByCodeAndGroup",
      "innerClass" : "ThingType",
      "params" : [ {
        "getter" : "valueOf",
        "innerClass" : "String",
        "params" : "SOH"
      }, {
        "getter" : "getByHierarchyCode",
        "innerClass" : "Group",
        "params" : "${tenant.hierarchyCode}"
      } ]
    },
    "thingTypeField" : {
      "getter" : "getByNameAndThingType",
      "innerClass" : "ThingTypeField",
      "params" : [ {
        "getter" : "valueOf",
        "innerClass" : "String",
        "params" : "Retail_Product_Level1Name"
      }, {
        "getter" : "getByCodeAndGroup",
        "innerClass" : "ThingType",
        "params" : [ {
          "getter" : "valueOf",
          "innerClass" : "String",
          "params" : "SOH"
        }, {
          "getter" : "getByHierarchyCode",
          "innerClass" : "Group",
          "params" : "${tenant.hierarchyCode}"
        } ]
      } ]
    },
    "fieldType" : 1,
    "value" : "",
    "operator" : "="
  },
  "RTI Owner" : {
    "autoComplete" : false,
    "reportDefinition" : {
      "getter" : "getByCodeAndHierarchyCode",
      "innerClass" : "ReportDefinition",
      "params" : [ {
        "getter" : "valueOf",
        "innerClass" : "String",
        "params" : "REALTIMEDISCREPANCY"
      }, {
        "getter" : "valueOf",
        "innerClass" : "String",
        "params" : "${tenant.hierarchyCode}"
      } ]
    },
    "propertyName" : "Retail_Product_Level2Name",
    "editable" : true,
    "displayOrder" : 7,
    "label" : "RTI Owner",
    "thingType" : {
      "getter" : "getByCodeAndGroup",
      "innerClass" : "ThingType",
      "params" : [ {
        "getter" : "valueOf",
        "innerClass" : "String",
        "params" : "SOH"
      }, {
        "getter" : "getByHierarchyCode",
        "innerClass" : "Group",
        "params" : "${tenant.hierarchyCode}"
      } ]
    },
    "thingTypeField" : {
      "getter" : "getByNameAndThingType",
      "innerClass" : "ThingTypeField",
      "params" : [ {
        "getter" : "valueOf",
        "innerClass" : "String",
        "params" : "Retail_Product_Level2Name"
      }, {
        "getter" : "getByCodeAndGroup",
        "innerClass" : "ThingType",
        "params" : [ {
          "getter" : "valueOf",
          "innerClass" : "String",
          "params" : "SOH"
        }, {
          "getter" : "getByHierarchyCode",
          "innerClass" : "Group",
          "params" : "${tenant.hierarchyCode}"
        } ]
      } ]
    },
    "fieldType" : 1,
    "value" : "",
    "operator" : "="
  },
  "RemainingTo" : {
    "autoComplete" : false,
    "reportDefinition" : {
      "getter" : "getByCodeAndHierarchyCode",
      "innerClass" : "ReportDefinition",
      "params" : [ {
        "getter" : "valueOf",
        "innerClass" : "String",
        "params" : "REALTIMEDISCREPANCY"
      }, {
        "getter" : "valueOf",
        "innerClass" : "String",
        "params" : "${tenant.hierarchyCode}"
      } ]
    },
    "propertyName" : "Retail_SOHQTY",
    "editable" : true,
    "displayOrder" : 12,
    "label" : "RemainingTo",
    "thingType" : {
      "getter" : "getByCodeAndGroup",
      "innerClass" : "ThingType",
      "params" : [ {
        "getter" : "valueOf",
        "innerClass" : "String",
        "params" : "SOH"
      }, {
        "getter" : "getByHierarchyCode",
        "innerClass" : "Group",
        "params" : "${tenant.hierarchyCode}"
      } ]
    },
    "thingTypeField" : {
      "getter" : "getByNameAndThingType",
      "innerClass" : "ThingTypeField",
      "params" : [ {
        "getter" : "valueOf",
        "innerClass" : "String",
        "params" : "Retail_SOHQTY"
      }, {
        "getter" : "getByCodeAndGroup",
        "innerClass" : "ThingType",
        "params" : [ {
          "getter" : "valueOf",
          "innerClass" : "String",
          "params" : "SOH"
        }, {
          "getter" : "getByHierarchyCode",
          "innerClass" : "Group",
          "params" : "${tenant.hierarchyCode}"
        } ]
      } ]
    },
    "fieldType" : 4,
    "value" : "",
    "operator" : "<="
  }
}